bioel/__init__.py
bioel/dataset.py
bioel/evaluate.py
bioel/linking_eval.py
bioel/logger.py
bioel/model.py
bioel/ontology.py
bioel/models/arboel/biencoder/evaluate_biencoder.py
bioel/models/arboel/biencoder/train_biencoder.py
bioel/models/arboel/biencoder/data/BiEncoderLightningDataModule.py
bioel/models/arboel/biencoder/data/data_process.py
bioel/models/arboel/biencoder/data/data_utils.py
bioel/models/arboel/biencoder/model/BiEncoderLightningModule.py
bioel/models/arboel/biencoder/model/biencoder.py
bioel/models/arboel/biencoder/model/eval_cluster_linking.py
bioel/models/arboel/biencoder/model/common/optimizer.py
bioel/models/arboel/biencoder/model/common/params.py
bioel/models/arboel/biencoder/model/common/ranker_base.py
bioel/models/arboel/biencoder/model/special_partition/setup.py
bioel/models/arboel/biencoder/model/special_partition/special_partition.pyx
bioel/models/arboel/crossencoder/evaluate_crossencoder.py
bioel/models/arboel/crossencoder/train_crossencoder.py
bioel/models/arboel/crossencoder/data/CrossEncoderLightningDataModule.py
bioel/models/arboel/crossencoder/data/top_cands.py
bioel/models/arboel/crossencoder/model/CrossEncoderLightningModule.py
bioel/models/arboel/crossencoder/model/crossencoder.py
bioel/models/biogenel/LightningDataModule.py
bioel/models/biogenel/LightningModule.py
bioel/models/biogenel/__init__.py
bioel/models/biogenel/data_processing.py
bioel/models/biogenel/eval_biogenel_biobart.py
bioel/models/biogenel/train_biogenel_biobart.py
bioel/models/biogenel/trainer.py
bioel/models/biogenel/utils.py
bioel/models/biogenel/fairseq_beam/__init__.py
bioel/models/biogenel/fairseq_beam/search.py
bioel/models/biogenel/fairseq_beam/sequence_generator.py
bioel/models/biogenel/fairseq_beam/sequence_scorer.py
bioel/models/biogenel/models/__init__.py
bioel/models/biogenel/models/bart_model.py
bioel/models/biogenel/models/beam_scorer.py
bioel/models/biogenel/models/prompt_bart.py
bioel/models/biogenel/models/prompt_t5.py
bioel_package_pathology_dynamics-0.0.1.dist-info/METADATA
bioel_package_pathology_dynamics-0.0.1.dist-info/WHEEL
bioel_package_pathology_dynamics-0.0.1.dist-info/licenses/LICENSE
bioel_package_pathology_dynamics-0.0.1.dist-info/RECORD
