Metadata-Version: 2.3
Name: bioel_package_pathology_dynamics
Version: 0.0.1
Summary: A biomedical entity-linking package
Project-URL: Homepage, https://github.com/davidkartchner/biomedical-entity-linking
Project-URL: Issues, https://github.com/davidkartchner/biomedical-entity-linking/issues
Author-email: Pathology Dynamics <cassie.mitchell@bme.gatech.edu>, Prasanth Bathala <bathalaprasanth@gmail.com>, Batuhan Nursal <bnursal3@gatech.edu>, Christophe Ye <cye73@gatech.edu>, Shubbam Lohiya <shubhlohiya@gatech.edu>, David Kartchner <davidkartchner@gmail.com>, Cassie Mitchell <cassie.mitchell@bme.gatech.edu>
License-File: LICENSE
Classifier: License :: OSI Approved :: MIT License
Classifier: Operating System :: OS Independent
Classifier: Programming Language :: Python :: 3
Requires-Python: >=3.9
